Metadata-Version: 2.1
Name: tapa
Version: 0.0.20240825.1
Summary: Extending High-Level Synthesis for Task-Parallel Programs
Home-page: https://github.com/UCLA-VAST/tapa
Author: Blaok Chi
Classifier: Development Status :: 2 - Pre-Alpha
Classifier: Intended Audience :: Developers
Classifier: Intended Audience :: Science/Research
Classifier: License :: OSI Approved :: MIT License
Classifier: Programming Language :: Python :: 3 :: Only
Classifier: Programming Language :: Python :: 3
Classifier: Programming Language :: Python :: 3.8
Classifier: Programming Language :: Python :: 3.9
Classifier: Programming Language :: Python :: 3.10
Classifier: Programming Language :: Python :: 3.11
Classifier: Programming Language :: Python :: 3.12
Classifier: Programming Language :: Python :: 3.13
Classifier: Topic :: System :: Hardware
Requires-Python: >=3.8
License-File: LICENSE
Requires-Dist: absl-py
Requires-Dist: autobridge >=0.0.20220512.dev1
Requires-Dist: coloredlogs >=9.3
Requires-Dist: haoda >=0.0.20240228.dev1
Requires-Dist: jinja2
Requires-Dist: pyverilog >=1.2.0
Requires-Dist: pyyaml >=5.1
Requires-Dist: tapa-fast-cosim >=0.0.20220514.dev1
Requires-Dist: toposort
Requires-Dist: click >=7.1.2
